{"word": "afloat", "definitions": [{"pos": "s", "text": "aimlessly drifting", "examples": [], "synonyms": ["adrift", "aimless", "directionless", "planless", "rudderless", "undirected"], "antonyms": []}, {"pos": "a", "text": "borne on the water; floating", "examples": [], "synonyms": [], "antonyms": ["aground"]}, {"pos": "s", "text": "covered with water", "examples": ["the main deck was afloat (or awash)", "the monsoon left the whole place awash", "a flooded bathroom", "inundated farmlands", "an overflowing tub"], "synonyms": ["awash", "flooded", "inundated", "overflowing"], "antonyms": []}]}