{"word": "modest", "definitions": [{"pos": "a", "text": "marked by simplicity; having a humble opinion of yourself", "examples": ["a modest apartment", "too modest to wear his medals"], "synonyms": [], "antonyms": ["immodest"]}, {"pos": "s", "text": "not large but sufficient in size or amount", "examples": ["a modest salary", "modest inflation", "helped in my own small way"], "synonyms": ["small"], "antonyms": []}, {"pos": "s", "text": "free from pomp or affectation", "examples": ["comfortable but modest cottages", "a simple rectangular brick building", "a simple man with simple tastes"], "synonyms": [], "antonyms": []}, {"pos": "a", "text": "not offensive to sexual mores in conduct or appearance", "examples": [], "synonyms": [], "antonyms": ["immodest"]}, {"pos": "s", "text": "low or inferior in station or quality", "examples": ["a humble cottage", "a lowly parish priest", "a modest man of the people", "small beginnings"], "synonyms": ["humble", "low", "lowly", "small"], "antonyms": []}, {"pos": "s", "text": "humble in spirit or manner; suggesting retiring mildness or even cowed submissiveness", "examples": ["meek and self-effacing"], "synonyms": ["meek", "mild"], "antonyms": []}, {"pos": "s", "text": "limited in size or scope", "examples": ["a small business", "a newspaper with a modest circulation", "small-scale plans", "a pocket-size country"], "synonyms": ["minor", "small", "small-scale", "pocket-size", "pocket-sized"], "antonyms": []}]}