{"word": "route", "definitions": [{"pos": "n", "text": "an established line of travel or access", "examples": [], "synonyms": ["path", "itinerary"], "antonyms": []}, {"pos": "n", "text": "an open way (generally public) for travel or transportation", "examples": [], "synonyms": ["road"], "antonyms": []}, {"pos": "v", "text": "send documents or materials to appropriate destinations", "examples": [], "synonyms": [], "antonyms": []}, {"pos": "v", "text": "send via a specific route", "examples": [], "synonyms": [], "antonyms": []}, {"pos": "v", "text": "divert in a specified direction", "examples": ["divert the low voltage to the engine cylinders"], "synonyms": [], "antonyms": []}]}