{"word": "slander", "definitions": [{"pos": "n", "text": "words falsely spoken that damage the reputation of another", "examples": [], "synonyms": [], "antonyms": []}, {"pos": "n", "text": "an abusive attack on a person's character or good name", "examples": [], "synonyms": ["aspersion", "calumny", "defamation", "denigration"], "antonyms": []}, {"pos": "v", "text": "charge falsely or with malicious intent; attack the good name and reputation of someone", "examples": ["The journalists have defamed me!", "The article in the paper sullied my reputation"], "synonyms": ["defame", "smirch", "asperse", "denigrate", "calumniate", "smear", "sully", "besmirch"], "antonyms": []}]}