{"word": "carter", "definitions": [{"pos": "n", "text": "Englishman and Egyptologist who in 1922 discovered and excavated the tomb of Tutankhamen (1873-1939)", "examples": [], "synonyms": ["Carter", "Howard Carter"], "antonyms": []}, {"pos": "n", "text": "39th President of the United States (1924-)", "examples": [], "synonyms": ["Carter", "Jimmy Carter", "James Earl Carter", "James Earl Carter Jr.", "President Carter"], "antonyms": []}, {"pos": "n", "text": "someone whose work is driving carts", "examples": [], "synonyms": [], "antonyms": []}]}