{"word": "depravity", "definitions": [{"pos": "n", "text": "moral perversion; impairment of virtue and moral principles", "examples": ["the luxury and corruption among the upper classes", "moral degeneracy followed intellectual degeneration", "its brothels, its opium parlors, its depravity", "Rome had fallen into moral putrefaction"], "synonyms": ["corruption", "degeneracy", "depravation", "putrefaction"], "antonyms": []}, {"pos": "n", "text": "a corrupt or depraved or degenerate act or practice", "examples": ["the various turpitudes of modern society"], "synonyms": ["turpitude"], "antonyms": []}]}