{"word": "upgrade", "definitions": [{"pos": "n", "text": "an upward slope or grade (as in a road)", "examples": ["the car couldn't make it up the rise"], "synonyms": ["ascent", "acclivity", "rise", "raise", "climb"], "antonyms": ["descent"]}, {"pos": "n", "text": "software that provides better performance than an earlier version did", "examples": [], "synonyms": [], "antonyms": []}, {"pos": "n", "text": "a reservation that is improved", "examples": ["I got an upgrade to first class when coach class was full"], "synonyms": [], "antonyms": []}, {"pos": "n", "text": "the property possessed by a slope or surface that rises", "examples": [], "synonyms": ["rise", "rising slope"], "antonyms": []}, {"pos": "n", "text": "hardware that provides better performance than an earlier version did", "examples": [], "synonyms": [], "antonyms": []}, {"pos": "n", "text": "the act of improving something (especially machinery) by raising it to a higher grade (as by adding or replacing components)", "examples": ["the power plant received a new upgrade"], "synonyms": [], "antonyms": []}, {"pos": "v", "text": "rate higher; raise in value or esteem", "examples": [], "synonyms": [], "antonyms": ["downgrade"]}, {"pos": "v", "text": "to improve what was old or outdated", "examples": ["I've upgraded my computer so I can run better software", "The company upgraded their personnel"], "synonyms": [], "antonyms": []}, {"pos": "v", "text": "give a promotion to or assign to a higher position", "examples": ["John was kicked upstairs when a replacement was hired", "Women tend not to advance in the major law firms", "I got promoted after many years of hard work"], "synonyms": ["promote", "advance", "kick upstairs", "raise", "elevate"], "antonyms": ["demote"]}, {"pos": "v", "text": "get better travel conditions", "examples": ["I upgraded to First Class when Coach Class was overbooked"], "synonyms": [], "antonyms": []}, {"pos": "v", "text": "give better travel conditions to", "examples": ["The airline upgraded me when I arrived late and Coach Class was full"], "synonyms": [], "antonyms": []}]}