{"word": "desire", "definitions": [{"pos": "n", "text": "the feeling that accompanies an unsatisfied state", "examples": [], "synonyms": [], "antonyms": []}, {"pos": "n", "text": "an inclination to want things", "examples": ["a man of many desires"], "synonyms": [], "antonyms": []}, {"pos": "n", "text": "something that is desired", "examples": [], "synonyms": [], "antonyms": []}, {"pos": "v", "text": "feel or have a desire for; want strongly", "examples": ["I want to go home now", "I want my own room"], "synonyms": ["want"], "antonyms": []}, {"pos": "v", "text": "expect and wish", "examples": ["I trust you will behave better from now on", "I hope she understands that she cannot expect a raise"], "synonyms": ["hope", "trust"], "antonyms": []}, {"pos": "v", "text": "express a desire for", "examples": [], "synonyms": [], "antonyms": []}]}