{"word": "eject", "definitions": [{"pos": "v", "text": "put out or expel from a place", "examples": ["The unruly student was excluded from the game"], "synonyms": ["chuck out", "exclude", "turf out", "boot out", "turn out"], "antonyms": []}, {"pos": "v", "text": "eliminate (a substance)", "examples": ["combustion products are exhausted in the engine", "the plant releases a gas"], "synonyms": ["exhaust", "discharge", "expel", "release"], "antonyms": []}, {"pos": "v", "text": "leave an aircraft rapidly, using an ejection seat or capsule", "examples": [], "synonyms": [], "antonyms": []}, {"pos": "v", "text": "cause to come out in a squirt", "examples": ["the boy squirted water at his little sister"], "synonyms": ["squirt", "force out", "squeeze out"], "antonyms": []}]}