{"word": "inmate", "definitions": [{"pos": "n", "text": "one of several resident of a dwelling (especially someone confined to a prison or hospital)", "examples": [], "synonyms": [], "antonyms": []}, {"pos": "n", "text": "a patient who is residing in the hospital where he is being treated", "examples": [], "synonyms": ["inpatient"], "antonyms": ["outpatient"]}, {"pos": "n", "text": "a person serving a sentence in a jail or prison", "examples": [], "synonyms": ["convict", "con", "yard bird", "yardbird"], "antonyms": []}]}