{"word": "conservative", "definitions": [{"pos": "n", "text": "a person who is reluctant to accept changes and new ideas", "examples": [], "synonyms": ["conservativist"], "antonyms": ["liberal"]}, {"pos": "n", "text": "a member of a Conservative Party", "examples": [], "synonyms": ["Conservative"], "antonyms": []}, {"pos": "a", "text": "resistant to change", "examples": [], "synonyms": [], "antonyms": ["liberal"]}, {"pos": "s", "text": "having social or political views favoring conservatism", "examples": [], "synonyms": [], "antonyms": []}, {"pos": "s", "text": "avoiding excess", "examples": ["a conservative estimate"], "synonyms": ["cautious"], "antonyms": []}, {"pos": "s", "text": "unimaginatively conventional; - Newsweek", "examples": ["a colorful character in the buttoned-down, dull-grey world of business"], "synonyms": ["button-down", "buttoned-down"], "antonyms": []}, {"pos": "s", "text": "conforming to the standards and conventions of the middle class", "examples": ["a bourgeois mentality"], "synonyms": ["bourgeois", "materialistic"], "antonyms": []}]}