{"word": "jibe", "definitions": [{"pos": "n", "text": "an aggressive remark directed at a person like a missile and intended to have a telling effect", "examples": ["his parting shot was `drop dead'", "she threw shafts of sarcasm", "she takes a dig at me every chance she gets"], "synonyms": ["shot", "shaft", "slam", "dig", "barb", "gibe"], "antonyms": []}, {"pos": "v", "text": "be compatible, similar or consistent; coincide in their characteristics", "examples": ["The two stories don't agree in many details", "The handwriting checks with the signature on the check", "The suspect's fingerprints don't match those on the gun"], "synonyms": ["match", "fit", "correspond", "check", "gibe", "tally", "agree"], "antonyms": ["disagree"]}, {"pos": "v", "text": "shift from one side of the ship to the other", "examples": ["The sail jibbed wildly"], "synonyms": ["gybe", "jib", "change course"], "antonyms": []}]}