{"word": "transport", "definitions": [{"pos": "n", "text": "something that serves as a means of transportation", "examples": [], "synonyms": ["conveyance"], "antonyms": []}, {"pos": "n", "text": "an exchange of molecules (and their kinetic energy and momentum) across the boundary between adjacent layers of a fluid or across cell membranes", "examples": [], "synonyms": [], "antonyms": []}, {"pos": "n", "text": "the commercial enterprise of moving goods and materials", "examples": [], "synonyms": ["shipping"], "antonyms": []}, {"pos": "n", "text": "a state of being carried away by overwhelming emotion; - Charles Dickens", "examples": ["listening to sweet music in a perfect rapture"], "synonyms": ["ecstasy", "rapture", "exaltation", "raptus"], "antonyms": []}, {"pos": "n", "text": "a mechanism that transports magnetic tape across the read/write heads of a tape playback/recorder", "examples": [], "synonyms": ["tape drive"], "antonyms": []}, {"pos": "n", "text": "the act of moving something from one location to another", "examples": [], "synonyms": ["transfer", "transferral", "conveyance"], "antonyms": []}, {"pos": "v", "text": "move something or somebody around; usually over long distances", "examples": [], "synonyms": [], "antonyms": []}, {"pos": "v", "text": "move while supporting, either in a vehicle or in one's hands or on one's body", "examples": ["You must carry your camping gear", "carry the suitcases to the car", "This train is carrying nuclear waste", "These pipes carry waste water into the river"], "synonyms": ["carry"], "antonyms": []}, {"pos": "v", "text": "hold spellbound", "examples": [], "synonyms": ["enchant", "enrapture", "enthrall", "ravish", "enthral", "delight"], "antonyms": ["disenchant"]}, {"pos": "v", "text": "transport commercially", "examples": [], "synonyms": ["send", "ship"], "antonyms": []}, {"pos": "v", "text": "send from one person or place to another", "examples": ["transmit a message"], "synonyms": ["transmit", "transfer", "channel", "channelize", "channelise"], "antonyms": []}]}