{"word": "crush", "definitions": [{"pos": "n", "text": "leather that has had its grain pattern accentuated", "examples": [], "synonyms": [], "antonyms": []}, {"pos": "n", "text": "a dense crowd of people", "examples": [], "synonyms": ["jam", "press"], "antonyms": []}, {"pos": "n", "text": "temporary love of an adolescent", "examples": [], "synonyms": ["puppy love", "calf love", "infatuation"], "antonyms": []}, {"pos": "n", "text": "the act of crushing", "examples": [], "synonyms": ["crunch", "compaction"], "antonyms": []}, {"pos": "v", "text": "come down on or keep down by unjust use of one's authority", "examples": ["The government oppresses political activists"], "synonyms": ["oppress", "suppress"], "antonyms": []}, {"pos": "v", "text": "to compress with violence, out of natural shape or condition", "examples": ["crush an aluminum can", "squeeze a lemon"], "synonyms": ["squash", "squelch", "mash", "squeeze"], "antonyms": []}, {"pos": "v", "text": "come out better in a competition, race, or conflict", "examples": ["Agassi beat Becker in the tennis championship", "We beat the competition", "Harvard defeated Yale in the last football game"], "synonyms": ["beat", "beat out", "shell", "trounce", "vanquish"], "antonyms": []}, {"pos": "v", "text": "break into small pieces", "examples": ["The car crushed the toy"], "synonyms": [], "antonyms": []}, {"pos": "v", "text": "humiliate or depress completely", "examples": ["She was crushed by his refusal of her invitation", "The death of her son smashed her"], "synonyms": ["smash", "demolish"], "antonyms": []}, {"pos": "v", "text": "crush or bruise", "examples": ["jam a toe"], "synonyms": ["jam"], "antonyms": []}, {"pos": "v", "text": "make ineffective", "examples": ["Martin Luther King tried to break down racial discrimination"], "synonyms": ["break down"], "antonyms": []}, {"pos": "v", "text": "become injured, broken, or distorted by pressure", "examples": ["The plastic bottle crushed against the wall"], "synonyms": [], "antonyms": []}]}