{"word": "likeness", "definitions": [{"pos": "n", "text": "similarity in appearance or character or nature between persons or things", "examples": ["man created God in his own likeness"], "synonyms": ["similitude"], "antonyms": ["unlikeness", "dissimilitude"]}, {"pos": "n", "text": "picture consisting of a graphic image of a person or thing", "examples": [], "synonyms": ["semblance"], "antonyms": []}, {"pos": "v", "text": "consider or describe as similar, equal, or analogous", "examples": ["We can compare the Han dynasty to the Romans", "You cannot equate success in financial matters with greed"], "synonyms": ["compare", "liken", "equate"], "antonyms": []}]}