{"word": "well", "definitions": [{"pos": "n", "text": "a deep hole or shaft dug or drilled to obtain water or oil or gas or brine", "examples": [], "synonyms": [], "antonyms": []}, {"pos": "n", "text": "a cavity or vessel used to contain liquid", "examples": [], "synonyms": [], "antonyms": []}, {"pos": "n", "text": "an abundant source", "examples": ["she was a well of information"], "synonyms": ["fountainhead"], "antonyms": []}, {"pos": "n", "text": "an open shaft through the floors of a building (as for a stairway)", "examples": [], "synonyms": [], "antonyms": []}, {"pos": "n", "text": "an enclosed compartment in a ship or plane for holding something as e.g. fish or a plane's landing gear or for protecting something as e.g. a ship's pumps", "examples": [], "synonyms": [], "antonyms": []}, {"pos": "v", "text": "come up, as of a liquid", "examples": ["Tears well in her eyes", "the currents well up"], "synonyms": [], "antonyms": []}, {"pos": "a", "text": "in good health especially after having suffered illness or injury", "examples": ["appears to be entirely well", "the wound is nearly well", "a well man", "I think I'm well; at least I feel well"], "synonyms": [], "antonyms": ["ill"]}, {"pos": "s", "text": "resulting favorably", "examples": ["it's a good thing that I wasn't there", "it is good that you stayed", "it is well that no one saw you", "all's well that ends well"], "synonyms": ["good"], "antonyms": []}, {"pos": "s", "text": "wise or advantageous and hence advisable", "examples": ["it would be well to start early"], "synonyms": [], "antonyms": []}, {"pos": "r", "text": "(often used as a combining form) in a good or proper or satisfactory manner or to a high standard (`good' is a nonstandard dialectal variant for `well')", "examples": ["the children behaved well", "a task well done", "the party went well", "he slept well", "a well-argued thesis", "a well-seasoned dish", "a well-planned party", "the baby can walk pretty good"], "synonyms": ["good"], "antonyms": ["ill"]}, {"pos": "r", "text": "thoroughly or completely; fully; often used as a combining form; ; ; ; ; ,", "examples": ["The problem is well understood", "she was well informed", "shake well before using", "in order to avoid food poisoning be sure the meat is well cooked", "well-done beef", "well-satisfied customers", "well-educated"], "synonyms": [], "antonyms": []}, {"pos": "r", "text": "indicating high probability; in all likelihood", "examples": ["I might well do it", "a mistake that could easily have ended in disaster", "you may well need your umbrella", "he could equally well be trying to deceive us"], "synonyms": ["easily"], "antonyms": []}, {"pos": "r", "text": "(used for emphasis or as an intensifier) entirely or fully", "examples": ["a book well worth reading", "was well aware of the difficulties ahead", "suspected only too well what might be going on"], "synonyms": [], "antonyms": []}, {"pos": "r", "text": "to a suitable or appropriate extent or degree", "examples": ["the project was well underway", "the fetus has well developed organs", "his father was well pleased with his grades"], "synonyms": [], "antonyms": []}, {"pos": "r", "text": "favorably; with approval", "examples": ["their neighbors spoke well of them", "he thought well of the book"], "synonyms": [], "antonyms": ["ill"]}, {"pos": "r", "text": "to a great extent or degree", "examples": ["I'm afraid the film was well over budget", "painting the room white made it seem considerably (or substantially) larger", "the house has fallen considerably in value", "the price went up substantially"], "synonyms": ["considerably", "substantially"], "antonyms": []}, {"pos": "r", "text": "with great or especially intimate knowledge", "examples": ["we knew them well"], "synonyms": ["intimately"], "antonyms": []}, {"pos": "r", "text": "with prudence or propriety", "examples": ["You would do well to say nothing more", "could not well refuse"], "synonyms": [], "antonyms": []}, {"pos": "r", "text": "with skill or in a pleasing manner", "examples": ["she dances well", "he writes well"], "synonyms": [], "antonyms": ["badly"]}, {"pos": "r", "text": "in a manner affording benefit or advantage", "examples": ["she married well", "The children were settled advantageously in Seattle"], "synonyms": ["advantageously"], "antonyms": ["badly", "disadvantageously"]}, {"pos": "r", "text": "in financial comfort", "examples": ["They live well", "she has been able to live comfortably since her husband died"], "synonyms": ["comfortably"], "antonyms": []}, {"pos": "r", "text": "without unusual distress or resentment; with good humor", "examples": ["took the joke well", "took the tragic news well"], "synonyms": [], "antonyms": ["badly"]}]}