{"word": "garbled", "definitions": [{"pos": "v", "text": "make false by mutilation or addition; as of a message or story", "examples": [], "synonyms": ["falsify", "distort", "garble", "warp"], "antonyms": []}, {"pos": "s", "text": "lacking orderly continuity", "examples": ["a confused set of instructions", "a confused dream about the end of the world", "disconnected fragments of a story", "scattered thoughts"], "synonyms": ["confused", "disconnected", "disjointed", "disordered", "illogical", "scattered", "unconnected"], "antonyms": []}]}