{"word": "cipher", "definitions": [{"pos": "n", "text": "a message written in a secret code", "examples": [], "synonyms": ["cypher"], "antonyms": []}, {"pos": "n", "text": "a mathematical element that when added to another number yields the same number", "examples": [], "synonyms": ["zero", "0", "nought", "cypher"], "antonyms": []}, {"pos": "n", "text": "a quantity of no importance", "examples": ["it looked like nothing I had ever seen before", "reduced to nil all the work we had done", "we racked up a pathetic goose egg", "it was all for naught", "I didn't hear zilch about it"], "synonyms": ["nothing", "nil", "nix", "nada", "null", "aught", "cypher", "goose egg", "naught", "zero", "zilch", "zip", "zippo"], "antonyms": []}, {"pos": "n", "text": "a person of no influence", "examples": [], "synonyms": ["cypher", "nobody", "nonentity"], "antonyms": []}, {"pos": "n", "text": "a secret method of writing", "examples": [], "synonyms": ["cypher", "cryptograph", "secret code"], "antonyms": []}, {"pos": "v", "text": "convert ordinary language into code", "examples": ["We should encode the message for security reasons"], "synonyms": ["code", "cypher", "encrypt", "inscribe", "write in code"], "antonyms": []}, {"pos": "v", "text": "make a mathematical calculation or computation", "examples": [], "synonyms": ["calculate", "cypher", "compute", "work out", "reckon", "figure"], "antonyms": []}]}