{"word": "copy", "definitions": [{"pos": "n", "text": "a reproduction of a written record (e.g. of a legal or school record)", "examples": [], "synonyms": ["transcript"], "antonyms": []}, {"pos": "n", "text": "a thing made to be similar or identical to another thing", "examples": ["she made a copy of the designer dress", "the clone was a copy of its ancestor"], "synonyms": [], "antonyms": []}, {"pos": "n", "text": "matter to be printed; exclusive of graphical materials", "examples": [], "synonyms": ["written matter"], "antonyms": []}, {"pos": "n", "text": "material suitable for a journalistic account", "examples": ["catastrophes make good copy"], "synonyms": [], "antonyms": []}, {"pos": "v", "text": "copy down as is", "examples": ["The students were made to copy the alphabet over and over"], "synonyms": [], "antonyms": []}, {"pos": "v", "text": "reproduce someone's behavior or looks", "examples": ["The mime imitated the passers-by", "Children often copy their parents or older siblings"], "synonyms": ["imitate", "simulate"], "antonyms": []}, {"pos": "v", "text": "reproduce or make an exact copy of", "examples": ["replicate the cell", "copy the genetic information"], "synonyms": ["replicate"], "antonyms": []}, {"pos": "v", "text": "make a replica of", "examples": ["copy that drawing", "re-create a picture by Rembrandt"], "synonyms": ["re-create"], "antonyms": []}]}