{"word": "burden", "definitions": [{"pos": "n", "text": "an onerous or difficult concern", "examples": ["the burden of responsibility", "that's a load off my mind"], "synonyms": ["load", "encumbrance", "incumbrance", "onus"], "antonyms": []}, {"pos": "n", "text": "weight to be borne or conveyed", "examples": [], "synonyms": ["load", "loading"], "antonyms": []}, {"pos": "n", "text": "the central meaning or theme of a speech or literary work", "examples": [], "synonyms": ["effect", "essence", "core", "gist"], "antonyms": []}, {"pos": "n", "text": "the central idea that is expanded in a document or discourse", "examples": [], "synonyms": [], "antonyms": []}, {"pos": "v", "text": "weight down with a load", "examples": [], "synonyms": ["burthen", "weight", "weight down"], "antonyms": ["unburden"]}, {"pos": "v", "text": "impose a task upon, assign a responsibility to", "examples": ["He charged her with cleaning up all the files over the weekend"], "synonyms": ["charge", "saddle"], "antonyms": []}]}