{"word": "frustration", "definitions": [{"pos": "n", "text": "the feeling that accompanies an experience of being thwarted in attaining your goals", "examples": [], "synonyms": ["defeat"], "antonyms": []}, {"pos": "n", "text": "an act of hindering someone's plans or efforts", "examples": [], "synonyms": ["thwarting", "foiling"], "antonyms": []}, {"pos": "n", "text": "a feeling of annoyance at being hindered or criticized", "examples": ["her constant complaints were the main source of his frustration"], "synonyms": [], "antonyms": []}]}