{"word": "cordial", "definitions": [{"pos": "n", "text": "strong highly flavored sweet liquor usually drunk after a meal", "examples": [], "synonyms": ["liqueur"], "antonyms": []}, {"pos": "s", "text": "diffusing warmth and friendliness", "examples": ["an affable smile", "an amiable gathering", "cordial relations", "a cordial greeting", "a genial host"], "synonyms": ["affable", "amiable", "genial"], "antonyms": []}, {"pos": "s", "text": "politely warm and friendly", "examples": ["a cordial handshake"], "synonyms": [], "antonyms": []}, {"pos": "s", "text": "sincerely or intensely felt", "examples": ["a cordial regard for his visitor's comfort", "a cordial abhorrence of waste"], "synonyms": [], "antonyms": []}]}