{"word": "textbook", "definitions": [{"pos": "n", "text": "a book prepared for use in schools or colleges", "examples": ["his economics textbook is in its tenth edition", "the professor wrote the text that he assigned students to buy"], "synonyms": ["text", "text edition", "schoolbook", "school text"], "antonyms": ["trade edition"]}, {"pos": "s", "text": "according to or characteristic of a casebook or textbook; typical", "examples": ["a casebook schizophrenic", "a textbook example"], "synonyms": ["casebook"], "antonyms": []}]}