{"word": "snarl", "definitions": [{"pos": "n", "text": "a vicious angry growl", "examples": [], "synonyms": [], "antonyms": []}, {"pos": "n", "text": "an angry vicious expression", "examples": [], "synonyms": [], "antonyms": []}, {"pos": "n", "text": "something jumbled or confused", "examples": ["a tangle of government regulations"], "synonyms": ["tangle", "maze"], "antonyms": []}, {"pos": "v", "text": "utter in an angry, sharp, or abrupt tone", "examples": ["The sales clerk snapped a reply at the angry customer", "The guard snarled at us"], "synonyms": ["snap"], "antonyms": []}, {"pos": "v", "text": "make a snarling noise or move with a snarling noise", "examples": ["Bullets snarled past us"], "synonyms": [], "antonyms": []}, {"pos": "v", "text": "twist together or entwine into a confusing mass", "examples": ["The child entangled the cord"], "synonyms": ["entangle", "tangle", "mat"], "antonyms": ["disentangle", "unsnarl"]}, {"pos": "v", "text": "make more complicated or confused through entanglements", "examples": [], "synonyms": ["embrangle"], "antonyms": []}]}