{"word": "pucker", "definitions": [{"pos": "n", "text": "an irregular fold in an otherwise even surface (as in cloth)", "examples": [], "synonyms": ["ruck"], "antonyms": []}, {"pos": "v", "text": "to gather something into small wrinkles or folds", "examples": ["She puckered her lips"], "synonyms": ["rumple", "cockle", "crumple", "knit"], "antonyms": []}, {"pos": "v", "text": "draw together into folds or puckers", "examples": [], "synonyms": ["gather", "tuck"], "antonyms": []}, {"pos": "v", "text": "become wrinkled or drawn together", "examples": ["her lips puckered"], "synonyms": ["ruck", "ruck up"], "antonyms": []}]}