{"word": "invite", "definitions": [{"pos": "n", "text": "a colloquial expression for invitation", "examples": ["he didn't get no invite to the party"], "synonyms": [], "antonyms": []}, {"pos": "v", "text": "increase the likelihood of", "examples": ["ask for trouble", "invite criticism"], "synonyms": ["ask for"], "antonyms": []}, {"pos": "v", "text": "invite someone to one's house", "examples": ["Can I invite you for dinner on Sunday night?"], "synonyms": ["ask over", "ask round"], "antonyms": []}, {"pos": "v", "text": "give rise to a desire by being attractive or inviting", "examples": ["the window displays tempted the shoppers"], "synonyms": ["tempt"], "antonyms": []}, {"pos": "v", "text": "ask someone in a friendly way to do something", "examples": [], "synonyms": ["bid"], "antonyms": []}, {"pos": "v", "text": "have as a guest", "examples": ["I invited them to a restaurant"], "synonyms": ["pay for"], "antonyms": []}, {"pos": "v", "text": "ask to enter", "examples": ["We invited the neighbors in for a cup of coffee"], "synonyms": ["ask in"], "antonyms": []}, {"pos": "v", "text": "request the participation or presence of", "examples": ["The organizers invite submissions of papers for the conference"], "synonyms": ["call for"], "antonyms": []}, {"pos": "v", "text": "express willingness to have in one's home or environs", "examples": ["The community warmly received the refugees"], "synonyms": ["receive", "take in"], "antonyms": []}]}