{"word": "underline", "definitions": [{"pos": "n", "text": "a line drawn underneath (especially under written matter)", "examples": [], "synonyms": ["underscore"], "antonyms": []}, {"pos": "v", "text": "give extra weight to (a communication)", "examples": ["Her gesture emphasized her words"], "synonyms": ["underscore", "emphasize", "emphasise"], "antonyms": []}, {"pos": "v", "text": "draw a line or lines underneath to call attention to", "examples": [], "synonyms": ["underscore"], "antonyms": []}]}