{"word": "caustic", "definitions": [{"pos": "n", "text": "any chemical substance that burns or destroys living tissue", "examples": [], "synonyms": [], "antonyms": []}, {"pos": "s", "text": "harsh or corrosive in tone", "examples": ["an acerbic tone piercing otherwise flowery prose", "a barrage of acid comments", "her acrid remarks make her many enemies", "bitter words", "blistering criticism", "caustic jokes about political assassination, talk-show hosts and medical ethics", "a sulfurous denunciation", "a vitriolic critique"], "synonyms": ["acerb", "acerbic", "acid", "acrid", "bitter", "blistering", "sulfurous", "sulphurous", "virulent", "vitriolic"], "antonyms": []}, {"pos": "s", "text": "of a substance, especially a strong acid; capable of destroying or eating away by chemical action", "examples": [], "synonyms": ["corrosive", "erosive", "vitriolic", "mordant"], "antonyms": []}]}