{"word": "persuasion", "definitions": [{"pos": "n", "text": "the act of persuading (or attempting to persuade); communication intended to induce belief or action", "examples": [], "synonyms": ["suasion"], "antonyms": ["dissuasion"]}, {"pos": "n", "text": "a personal belief or judgment that is not founded on proof or certainty", "examples": ["my opinion differs from yours", "I am not of your persuasion", "what are your thoughts on Haiti?"], "synonyms": ["opinion", "sentiment", "view", "thought"], "antonyms": []}]}