{"word": "compression", "definitions": [{"pos": "n", "text": "an increase in the density of something", "examples": [], "synonyms": ["compaction", "concretion", "densification"], "antonyms": []}, {"pos": "n", "text": "the process or result of becoming smaller or pressed together", "examples": ["the contraction of a gas on cooling"], "synonyms": ["condensation", "contraction"], "antonyms": []}, {"pos": "n", "text": "encoding information while reducing the bandwidth or bits required", "examples": [], "synonyms": [], "antonyms": ["decompression"]}, {"pos": "n", "text": "applying pressure", "examples": [], "synonyms": ["compressing"], "antonyms": ["decompression"]}]}