{"word": "rotation", "definitions": [{"pos": "n", "text": "the act of rotating as if on an axis", "examples": ["the rotation of the dancer kept time with the music"], "synonyms": ["rotary motion"], "antonyms": []}, {"pos": "n", "text": "(mathematics) a transformation in which the coordinate axes are rotated by a fixed angle about the origin", "examples": [], "synonyms": [], "antonyms": []}, {"pos": "n", "text": "a single complete turn (axial or orbital)", "examples": ["the plane made three rotations before it crashed", "the revolution of the earth about the sun takes one year"], "synonyms": ["revolution", "gyration"], "antonyms": []}, {"pos": "n", "text": "a planned recurrent sequence (of crops or personnel etc.)", "examples": ["crop rotation makes a balanced demand on the fertility of the soil", "the manager had only four starting pitchers in his rotation"], "synonyms": [], "antonyms": []}]}