{"word": "rebound", "definitions": [{"pos": "n", "text": "a movement back from an impact", "examples": [], "synonyms": ["recoil", "repercussion", "backlash"], "antonyms": []}, {"pos": "n", "text": "a reaction to a crisis or setback or frustration", "examples": ["he is still on the rebound from his wife's death"], "synonyms": [], "antonyms": []}, {"pos": "n", "text": "the act of securing possession of the rebounding basketball after a missed shot", "examples": [], "synonyms": [], "antonyms": []}, {"pos": "v", "text": "spring back; spring away from an impact", "examples": ["The rubber ball bounced", "These particles do not resile but they unite after they collide"], "synonyms": ["bounce", "resile", "take a hop", "spring", "bound", "recoil", "reverberate", "ricochet"], "antonyms": []}, {"pos": "v", "text": "return to a former condition", "examples": ["The jilted lover soon rallied and found new friends", "The stock market rallied"], "synonyms": ["rally"], "antonyms": []}]}