{"word": "juvenile", "definitions": [{"pos": "n", "text": "a young person, not fully developed", "examples": [], "synonyms": [], "antonyms": ["adult"]}, {"pos": "a", "text": "of or relating to or characteristic of or appropriate for children or young people", "examples": ["juvenile diabetes", "juvenile fashions"], "synonyms": [], "antonyms": []}, {"pos": "s", "text": "displaying or suggesting a lack of maturity", "examples": ["adolescent insecurity", "jejune responses to our problems", "their behavior was juvenile", "puerile jokes"], "synonyms": ["adolescent", "jejune", "puerile"], "antonyms": []}]}