{"word": "shout", "definitions": [{"pos": "n", "text": "a loud utterance; often in protest or opposition", "examples": ["the speaker was interrupted by loud cries from the rear of the audience"], "synonyms": ["cry", "outcry", "call", "yell", "vociferation"], "antonyms": []}, {"pos": "v", "text": "utter in a loud voice; talk in a loud voice (usually denoting characteristic manner of speaking)", "examples": ["My grandmother is hard of hearing--you'll have to shout"], "synonyms": [], "antonyms": ["whisper"]}, {"pos": "v", "text": "utter a sudden loud cry", "examples": ["she cried with pain when the doctor inserted the needle", "I yelled to her from the window but she couldn't hear me"], "synonyms": ["cry", "call", "yell", "scream", "holler", "hollo", "squall"], "antonyms": []}, {"pos": "v", "text": "utter aloud; often with surprise, horror, or joy", "examples": ["`I won!' he exclaimed", "`Help!' she cried", "`I'm here,' the mother shouted when she saw her child looking lost"], "synonyms": ["exclaim", "cry", "cry out", "outcry", "call out"], "antonyms": []}, {"pos": "v", "text": "use foul or abusive language towards", "examples": ["The actress abused the policeman who gave her a parking ticket", "The angry mother shouted at the teacher"], "synonyms": ["abuse", "clapperclaw", "blackguard"], "antonyms": []}]}