{"word": "privy", "definitions": [{"pos": "n", "text": "a room or building equipped with one or more toilets", "examples": [], "synonyms": ["toilet", "lavatory", "lav", "can", "john", "bathroom"], "antonyms": []}, {"pos": "n", "text": "a small outbuilding with a bench having holes through which a user can defecate", "examples": [], "synonyms": ["outhouse", "earth-closet", "jakes"], "antonyms": []}, {"pos": "s", "text": "hidden from general view or use", "examples": ["a privy place to rest and think", "a secluded romantic spot", "a secret garden"], "synonyms": ["secluded", "secret"], "antonyms": []}, {"pos": "s", "text": "(followed by `to') informed about something secret or not generally known", "examples": ["privy to the details of the conspiracy"], "synonyms": [], "antonyms": []}]}