{"word": "yellow", "definitions": [{"pos": "n", "text": "yellow color or pigment; the chromatic color resembling the hue of sunflowers or ripe lemons", "examples": [], "synonyms": [], "antonyms": []}, {"pos": "v", "text": "turn yellow", "examples": ["The pages of the book began to yellow"], "synonyms": [], "antonyms": []}, {"pos": "s", "text": "of the color intermediate between green and orange in the color spectrum; of something resembling the color of an egg yolk", "examples": [], "synonyms": ["xanthous"], "antonyms": []}, {"pos": "s", "text": "easily frightened", "examples": [], "synonyms": ["chicken", "chickenhearted", "lily-livered", "white-livered"], "antonyms": []}, {"pos": "s", "text": "changed to a yellowish color by age", "examples": ["yellowed parchment"], "synonyms": [], "antonyms": []}, {"pos": "s", "text": "typical of tabloids", "examples": ["sensational journalistic reportage of the scandal", "yellow press"], "synonyms": ["scandalmongering", "sensationalistic"], "antonyms": []}, {"pos": "s", "text": "cowardly or treacherous; -M.W.Straight", "examples": ["the little yellow stain of treason", "too yellow to stand and fight"], "synonyms": [], "antonyms": []}, {"pos": "s", "text": "affected by jaundice which causes yellowing of skin etc", "examples": [], "synonyms": ["jaundiced", "icteric"], "antonyms": []}]}