{"word": "firebird", "definitions": [{"pos": "n", "text": "the male is bright red with black wings and tail", "examples": [], "synonyms": ["scarlet tanager", "Piranga olivacea", "redbird"], "antonyms": []}, {"pos": "n", "text": "eastern subspecies of northern oriole", "examples": [], "synonyms": ["Baltimore oriole", "Baltimore bird", "hangbird", "Icterus galbula galbula"], "antonyms": []}, {"pos": "n", "text": "tropical American flycatcher found as far north as southern Texas and Arizona; adult male has bright scarlet and black plumage", "examples": [], "synonyms": ["vermillion flycatcher", "Pyrocephalus rubinus mexicanus"], "antonyms": []}]}