{"word": "notation", "definitions": [{"pos": "n", "text": "a technical system of symbols used to represent special things", "examples": [], "synonyms": [], "antonyms": []}, {"pos": "n", "text": "a comment or instruction (usually added)", "examples": ["his notes were appended at the end of the article", "he added a short notation to the address on the envelope"], "synonyms": ["note"], "antonyms": []}, {"pos": "n", "text": "the activity of representing something by a special system of marks or characters", "examples": [], "synonyms": [], "antonyms": []}]}