{"word": "laden", "definitions": [{"pos": "v", "text": "remove with or as if with a ladle", "examples": ["ladle the water out of the bowl"], "synonyms": ["ladle", "lade"], "antonyms": []}, {"pos": "v", "text": "fill or place a load on", "examples": ["load a car", "load the truck with hay"], "synonyms": ["load", "lade", "load up"], "antonyms": []}, {"pos": "v", "text": "remove with or as if with a ladle", "examples": ["ladle the water out of the bowl"], "synonyms": ["ladle", "lade"], "antonyms": []}, {"pos": "v", "text": "fill or place a load on", "examples": ["load a car", "load the truck with hay"], "synonyms": ["load", "lade", "load up"], "antonyms": []}, {"pos": "s", "text": "filled with a great quantity", "examples": ["a tray loaded with dishes", "table laden with food", "`ladened' is not current usage"], "synonyms": ["loaded"], "antonyms": []}, {"pos": "s", "text": "burdened psychologically or mentally", "examples": ["laden with grief", "oppressed by a sense of failure"], "synonyms": ["oppressed"], "antonyms": []}]}