{"word": "sas", "definitions": [{"pos": "n", "text": "a specialist regiment of the British army that is trained in commando techniques of warfare and used in clandestine operations (especially against terrorist groups)", "examples": [], "synonyms": ["Special Air Service", "SAS"], "antonyms": []}, {"pos": "n", "text": "Nazi militia created by Hitler in 1921 that helped him to power but was eclipsed by the SS after 1943", "examples": [], "synonyms": ["SA", "Sturmabteilung", "Storm Troops"], "antonyms": []}]}