{"word": "vicarious", "definitions": [{"pos": "s", "text": "experienced at secondhand", "examples": ["read about mountain climbing and felt vicarious excitement"], "synonyms": [], "antonyms": []}, {"pos": "s", "text": "occurring in an abnormal part of the body instead of the usual site involved in that function", "examples": ["vicarious menstruation"], "synonyms": [], "antonyms": []}, {"pos": "s", "text": "suffered or done by one person as a substitute for another", "examples": ["vicarious atonement"], "synonyms": [], "antonyms": []}]}