{"word": "civilized", "definitions": [{"pos": "v", "text": "teach or refine to be discriminative in taste or judgment", "examples": ["Cultivate your musical taste", "Train your tastebuds", "She is well schooled in poetry"], "synonyms": ["educate", "school", "train", "cultivate", "civilize", "civilise"], "antonyms": []}, {"pos": "v", "text": "raise from a barbaric to a civilized state", "examples": ["The wild child found wandering in the forest was gradually civilized"], "synonyms": ["civilize", "civilise"], "antonyms": []}, {"pos": "a", "text": "having a high state of culture and development both social and technological", "examples": ["terrorist acts that shocked the civilized world"], "synonyms": ["civilised"], "antonyms": ["noncivilized"]}, {"pos": "s", "text": "marked by refinement in taste and manners", "examples": ["cultivated speech", "cultured Bostonians", "cultured tastes", "a genteel old lady", "polite society"], "synonyms": ["civilised", "cultivated", "cultured", "genteel", "polite"], "antonyms": []}]}