{"word": "fenced", "definitions": [{"pos": "v", "text": "enclose with a fence", "examples": ["we fenced in our yard"], "synonyms": ["fence", "fence in"], "antonyms": []}, {"pos": "v", "text": "receive stolen goods", "examples": [], "synonyms": ["fence"], "antonyms": []}, {"pos": "v", "text": "fight with fencing swords", "examples": [], "synonyms": ["fence"], "antonyms": []}, {"pos": "v", "text": "surround with a wall in order to fortify", "examples": [], "synonyms": ["wall", "palisade", "fence", "fence in", "surround"], "antonyms": []}, {"pos": "v", "text": "have an argument about something", "examples": [], "synonyms": ["argue", "contend", "debate", "fence"], "antonyms": []}]}