{"word": "bullshit", "definitions": [{"pos": "n", "text": "obscene words for unacceptable behavior", "examples": ["I put up with a lot of bullshit from that jerk", "what he said was mostly bull"], "synonyms": ["bull", "Irish bull", "horseshit", "shit", "crap", "dogshit"], "antonyms": []}, {"pos": "v", "text": "speak insincerely or without regard for facts or truths", "examples": ["The politician was not well prepared for the debate and faked it"], "synonyms": ["talk through one's hat", "bull", "fake"], "antonyms": []}]}