{"word": "refuge", "definitions": [{"pos": "n", "text": "a safe place", "examples": ["He ran to safety"], "synonyms": ["safety"], "antonyms": []}, {"pos": "n", "text": "something or someone turned to for assistance or security", "examples": ["his only recourse was the police", "took refuge in lying"], "synonyms": ["recourse", "resort"], "antonyms": []}, {"pos": "n", "text": "a shelter from danger or hardship", "examples": [], "synonyms": ["sanctuary", "asylum"], "antonyms": []}, {"pos": "n", "text": "act of turning to for assistance", "examples": ["have recourse to the courts", "an appeal to his uncle was his last resort"], "synonyms": ["recourse", "resort"], "antonyms": []}]}